trm/__init__.py
trm/trm.py
trm_woodburn-0.1.4.dist-info/LICENSE.txt
trm_woodburn-0.1.4.dist-info/METADATA
trm_woodburn-0.1.4.dist-info/WHEEL
trm_woodburn-0.1.4.dist-info/top_level.txt
trm_woodburn-0.1.4.dist-info/RECORD
