Metadata-Version: 2.1
Name: trm-woodburn
Version: 0.1.4
Summary: A library for pretty printing to the terminal
Home-page: https://gitlab.com/davidwoodburn/trm
Author: David Woodburn
Author-email: david.woodburn@icloud.com
Classifier: Programming Language :: Python :: 3
Classifier: License :: OSI Approved :: MIT License
Classifier: Operating System :: OS Independent
Requires-Python: >=3.6
License-File: LICENSE.txt
Requires-Dist: numpy
